[
  { "id": "CCN", "name": "Customer Care Network|361750680" },
  { "id": "FLO", "name": "FLS Outlet Stores|361750680" },
  { "id": "FBA", "name": "Florida Builder Appliances Inc|363619133" },
  { "id": "GRI", "name": "Great Indoors|361750680" },
  { "id": "HCN", "name": "Home Services Customer Support|361750680" },
  { "id": "HPS", "name": "Home Services Product Services|361750680" },
  { "id": "HSV", "name": "Home Services Support|361750680" },
  { "id": "HIS", "name": "HomeServices Home Improvement|361750680" },
  { "id": "HSC", "name": "HomeServices ServiceContracts|361750680" },
  { "id": "MCP", "name": "McPhail's Appliance|680406327" },
  { "id": "OSH", "name": "Orchard Supply Hardware|954214111" },
  { "id": "PCS", "name": "Puerto Rico Commercial Sales|660233626" },
  { "id": "PRF", "name": "Puerto Rico Full Line Stores|660233626" },
  { "id": "PHS", "name": "Puerto Rico Home Services|660233626" },
  { "id": "PRO", "name": "Puerto Rico Outlet Store|660233626" },
  { "id": "PPS", "name": "Puerto Rico Product Services|660233626" },
  { "id": "PSL", "name": "Puerto Rico Sears Logistics|660233626" },
  { "id": "PSC", "name": "Puerto Rico Service Contracts|660233626" },
  { "id": "PTG", "name": "Puerto Rico Tire Group|660233626" },
  { "id": "DLS", "name": "Sears Authorized Dealer Stores|361750680" },
  { "id": "SCU", "name": "Sears Carpet And Upholstery|980126742" },
  { "id": "CMS", "name": "Sears Commercial Sales|361750680" },
  { "id": "SEC", "name": "Sears Executive Committee|361750680" },
  { "id": "FLS", "name": "Sears Full Line Stores|361750680" },
  { "id": "SHS", "name": "Sears Hardware Stores|361750680" },
  { "id": "SMC", "name": "Sears Holdings Management Corp|203592148" },
  { "id": "SHP", "name": "Sears Home Imp Products|251698591" },
  { "id": "SLS", "name": "Sears Logistic Services|361857180" },
  { "id": "SLG", "name": "Sears Logistics Group|361750680" },
  { "id": "VGC", "name": "Sears Promotions, LLC|361750680" },
  { "id": "SPC", "name": "Sears Protection Company|364471250" },
  { "id": "SRA", "name": "Sears Roebuck Acceptance Corp|510080535" },
  { "id": "SRO", "name": "Sears Roebuck Corporate Func|361750680" },
  { "id": "STG", "name": "Sears Tire Group|361750680" },
  { "id": "SOE", "name": "Standard of Excellence,LLC|830399616" },
  { "id": "STW", "name": "Westar Kitchen and Bath|371495379" }
]
